sabrpkg/__init__.py
sabrpkg/metrics.py
SABRKBO-0.1.dist-info/LICENSE
SABRKBO-0.1.dist-info/METADATA
SABRKBO-0.1.dist-info/WHEEL
SABRKBO-0.1.dist-info/top_level.txt
SABRKBO-0.1.dist-info/RECORD
