Metadata-Version: 2.1
Name: SABRKBO
Version: 0.1
Summary: metrics calculator for Python
Home-page: https://github.com/YJPark0421/SABRKBO
Author: yjpark
Author-email: yjpark200421@gmail.com
License: MIT License
Keywords: SABRmetrics,SABR,baseball,stat,MLB,KBO,NPB
Classifier: Development Status :: 5 - Production/Stable
Classifier: Intended Audience :: Science/Research
Classifier: License :: OSI Approved :: MIT License
Classifier: Natural Language :: English
Classifier: Programming Language :: Python :: 3
License-File: LICENSE
